sfcv/__init__.py
sfcv/datasplit.py
sfcv/logdmodel.txt
sfcv/utils.py
sfcv-0.1.3.dist-info/licenses/LICENSE
sfcv-0.1.3.dist-info/METADATA
sfcv-0.1.3.dist-info/WHEEL
sfcv-0.1.3.dist-info/top_level.txt
sfcv-0.1.3.dist-info/RECORD
