Metadata-Version: 2.4
Name: sfcv
Version: 0.1.3
Summary: Step Forward Cross Validation for Bioactivity Prediction
Author: Manas Mahale
Author-email: manas.m.mahale@gmail.com
License: Apache 2.0
Requires-Python: >=3.11
License-File: LICENSE
Requires-Dist: joblib==1.5.1
Requires-Dist: lightgbm==4.6.0
Requires-Dist: molvs==0.1.1
Requires-Dist: numpy==2.3.2
Requires-Dist: pandas==2.3.2
Requires-Dist: rdkit==2025.3.5
Requires-Dist: scikit_learn==1.7.1
Requires-Dist: setuptools==80.9.0
Requires-Dist: tqdm==4.67.1
Requires-Dist: tqdm_joblib==0.0.5
Requires-Dist: xgboost==3.0.4
Dynamic: author
Dynamic: author-email
Dynamic: description
Dynamic: description-content-type
Dynamic: license
Dynamic: license-file
Dynamic: requires-dist
Dynamic: requires-python
Dynamic: summary
